RsCMPX_NiotMeas/RsCMPX_NiotMeas.py
RsCMPX_NiotMeas/__init__.py
RsCMPX_NiotMeas/enums.py
RsCMPX_NiotMeas/repcap.py
RsCMPX_NiotMeas/CustomFiles/__init__.py
RsCMPX_NiotMeas/CustomFiles/events.py
RsCMPX_NiotMeas/CustomFiles/reliability.py
RsCMPX_NiotMeas/CustomFiles/utilities.py
RsCMPX_NiotMeas/Implementations/__init__.py
RsCMPX_NiotMeas/Implementations/Configure/__init__.py
RsCMPX_NiotMeas/Implementations/Configure/NiotMeas/RfSettings.py
RsCMPX_NiotMeas/Implementations/Configure/NiotMeas/__init__.py
RsCMPX_NiotMeas/Implementations/Configure/NiotMeas/MultiEval/Pdynamics.py
RsCMPX_NiotMeas/Implementations/Configure/NiotMeas/MultiEval/Result.py
RsCMPX_NiotMeas/Implementations/Configure/NiotMeas/MultiEval/Subcarrier.py
RsCMPX_NiotMeas/Implementations/Configure/NiotMeas/MultiEval/__init__.py
RsCMPX_NiotMeas/Implementations/Configure/NiotMeas/MultiEval/Limit/EvMagnitude.py
RsCMPX_NiotMeas/Implementations/Configure/NiotMeas/MultiEval/Limit/FreqError.py
RsCMPX_NiotMeas/Implementations/Configure/NiotMeas/MultiEval/Limit/IqOffset.py
RsCMPX_NiotMeas/Implementations/Configure/NiotMeas/MultiEval/Limit/Merror.py
RsCMPX_NiotMeas/Implementations/Configure/NiotMeas/MultiEval/Limit/Pdynamics.py
RsCMPX_NiotMeas/Implementations/Configure/NiotMeas/MultiEval/Limit/Perror.py
RsCMPX_NiotMeas/Implementations/Configure/NiotMeas/MultiEval/Limit/__init__.py
RsCMPX_NiotMeas/Implementations/Configure/NiotMeas/MultiEval/Limit/Aclr/Gsm.py
RsCMPX_NiotMeas/Implementations/Configure/NiotMeas/MultiEval/Limit/Aclr/Utra.py
RsCMPX_NiotMeas/Implementations/Configure/NiotMeas/MultiEval/Limit/Aclr/__init__.py
RsCMPX_NiotMeas/Implementations/Configure/NiotMeas/MultiEval/Limit/Ibe/IqOffset.py
RsCMPX_NiotMeas/Implementations/Configure/NiotMeas/MultiEval/Limit/Ibe/__init__.py
RsCMPX_NiotMeas/Implementations/Configure/NiotMeas/MultiEval/Limit/SeMask/Limit.py
RsCMPX_NiotMeas/Implementations/Configure/NiotMeas/MultiEval/Limit/SeMask/__init__.py
RsCMPX_NiotMeas-5.0.70.dist-info/METADATA
RsCMPX_NiotMeas-5.0.70.dist-info/WHEEL
RsCMPX_NiotMeas-5.0.70.dist-info/top_level.txt
RsCMPX_NiotMeas-5.0.70.dist-info/RECORD
